sahara_plugin_cdh/__init__.py
sahara_plugin_cdh/i18n.py
sahara_plugin_cdh/locale/de/LC_MESSAGES/sahara_plugin_cdh.po
sahara_plugin_cdh/plugins/__init__.py
sahara_plugin_cdh/plugins/cdh/__init__.py
sahara_plugin_cdh/plugins/cdh/abstractversionhandler.py
sahara_plugin_cdh/plugins/cdh/cloudera_utils.py
sahara_plugin_cdh/plugins/cdh/commands.py
sahara_plugin_cdh/plugins/cdh/config_helper.py
sahara_plugin_cdh/plugins/cdh/confighints_helper.py
sahara_plugin_cdh/plugins/cdh/db_helper.py
sahara_plugin_cdh/plugins/cdh/deploy.py
sahara_plugin_cdh/plugins/cdh/edp_engine.py
sahara_plugin_cdh/plugins/cdh/exceptions.py
sahara_plugin_cdh/plugins/cdh/health.py
sahara_plugin_cdh/plugins/cdh/plugin.py
sahara_plugin_cdh/plugins/cdh/plugin_utils.py
sahara_plugin_cdh/plugins/cdh/validation.py
sahara_plugin_cdh/plugins/cdh/versionfactory.py
sahara_plugin_cdh/plugins/cdh/client/__init__.py
sahara_plugin_cdh/plugins/cdh/client/api_client.py
sahara_plugin_cdh/plugins/cdh/client/clusters.py
sahara_plugin_cdh/plugins/cdh/client/cms.py
sahara_plugin_cdh/plugins/cdh/client/hosts.py
sahara_plugin_cdh/plugins/cdh/client/http_client.py
sahara_plugin_cdh/plugins/cdh/client/resource.py
sahara_plugin_cdh/plugins/cdh/client/role_config_groups.py
sahara_plugin_cdh/plugins/cdh/client/roles.py
sahara_plugin_cdh/plugins/cdh/client/services.py
sahara_plugin_cdh/plugins/cdh/client/types.py
sahara_plugin_cdh/plugins/cdh/client/users.py
sahara_plugin_cdh/plugins/cdh/db_resources/create_hive_db.sql
sahara_plugin_cdh/plugins/cdh/db_resources/create_sentry_db.sql
sahara_plugin_cdh/plugins/cdh/v5_11_0/__init__.py
sahara_plugin_cdh/plugins/cdh/v5_11_0/cloudera_utils.py
sahara_plugin_cdh/plugins/cdh/v5_11_0/config_helper.py
sahara_plugin_cdh/plugins/cdh/v5_11_0/deploy.py
sahara_plugin_cdh/plugins/cdh/v5_11_0/edp_engine.py
sahara_plugin_cdh/plugins/cdh/v5_11_0/images.py
sahara_plugin_cdh/plugins/cdh/v5_11_0/plugin_utils.py
sahara_plugin_cdh/plugins/cdh/v5_11_0/validation.py
sahara_plugin_cdh-10.0.0.dist-info/AUTHORS
sahara_plugin_cdh-10.0.0.dist-info/LICENSE
sahara_plugin_cdh-10.0.0.dist-info/METADATA
sahara_plugin_cdh-10.0.0.dist-info/WHEEL
sahara_plugin_cdh-10.0.0.dist-info/entry_points.txt
sahara_plugin_cdh-10.0.0.dist-info/pbr.json
sahara_plugin_cdh-10.0.0.dist-info/top_level.txt
sahara_plugin_cdh-10.0.0.dist-info/RECORD
